toxic_classifier/__init__.py
toxic_classifier/model.py
toxic_classifier/utils.py
toxic_classifier/model/model.weights.h5
toxic_classifier/model/tokenizer.pickle
toxic_comment_classifier-0.3.0.dist-info/METADATA
toxic_comment_classifier-0.3.0.dist-info/WHEEL
toxic_comment_classifier-0.3.0.dist-info/top_level.txt
toxic_comment_classifier-0.3.0.dist-info/RECORD
