Metadata-Version: 2.4
Name: toxic_comment_classifier
Version: 0.3.0
Summary:  A Python library for classifying toxic comments using deep learning. It supports detecting multiple types of toxicity including obscene language, threats, and identity hate.
Author-email: Md Irfan Ali <irfanali29@hotmail.com>
License: MIT
Project-URL: Homepage, https://github.com/irfanalidv/toxic_comment_classifier
Project-URL: Repository, https://github.com/irfanalidv/toxic_comment_classifier
Project-URL: Issues, https://github.com/irfanalidv/toxic_comment_classifier/issues
Classifier: Programming Language :: Python :: 3
Classifier: License :: OSI Approved :: MIT License
Classifier: Operating System :: OS Independent
Requires-Python: >=3.6
Requires-Dist: numpy
Requires-Dist: tensorflow
Requires-Dist: pandas
Requires-Dist: scikit-learn
